README.md
setup.py
alibabacloud_imagesearch20200212/__init__.py
alibabacloud_imagesearch20200212/client.py
alibabacloud_imagesearch20200212/models.py
alibabacloud_imagesearch20200212.egg-info/PKG-INFO
alibabacloud_imagesearch20200212.egg-info/SOURCES.txt
alibabacloud_imagesearch20200212.egg-info/dependency_links.txt
alibabacloud_imagesearch20200212.egg-info/requires.txt
alibabacloud_imagesearch20200212.egg-info/top_level.txt